game_of_life/__init__.py
game_of_life/__main__.py
game_of_life_animation-0.1.2.dist-info/METADATA
game_of_life_animation-0.1.2.dist-info/WHEEL
game_of_life_animation-0.1.2.dist-info/entry_points.txt
game_of_life_animation-0.1.2.dist-info/top_level.txt
game_of_life_animation-0.1.2.dist-info/RECORD
