Metadata-Version: 2.1
Name: game-of-life-animation
Version: 0.1.2
Summary: A simple implementation of Conway's Game of Life using Python. Uses ascii-animator to animate the game to the terminal.
Author-email: Emilio Reyes <soda480@gmail.com>
Project-URL: Homepage, https://github.com/soda480/game-of-life
Classifier: Programming Language :: Python :: 3
Classifier: License :: OSI Approved :: Apache Software License
Classifier: Operating System :: OS Independent
Requires-Python: >=3.7
Requires-Dist: ascii-animator ==0.2.1
Provides-Extra: deploy
Requires-Dist: build ; extra == 'deploy'
Requires-Dist: twine ; extra == 'deploy'
Requires-Dist: setuptools >=61.0 ; extra == 'deploy'
